{
    "type": "Feature",
    "properties": {
        "type": "food",
        "name": "Bar Dobry",
        "desc": "Bar Dobry",
        "center": [
            18.61296415329,
            54.372589806704
        ]
    },
    "id": "bardobry",
    "geometry": {
        "type": "Polygon",
        "coordinates": [
            [
                [
                    18.612792491913,
                    54.372752297921
                ],
                [
                    18.613232374191,
                    54.372696051034
                ],
                [
                    18.61307144165,
                    54.372427314844
                ],
                [
                    18.612674474716,
                    54.372502311167
                ],
                [
                    18.612792491913,
                    54.372752297921
                ]
            ]
        ]
    }
}